{
  "data": {
    "091e2e9d39eefcb23258052624b61f043d6ffbae": [
      {
        "branch-instructions": 2566568312,
        "branch-misses": 6117736,
        "cycles": 8103922268,
        "instructions": 9290141749,
        "sysy_time": 5.403711,
        "task-clock": 5402.65
      },
      {
        "branch-instructions": 2566206228,
        "branch-misses": 5963524,
        "cycles": 8053729096,
        "instructions": 9287422674,
        "sysy_time": 5.380859,
        "task-clock": 5369.19
      },
      {
        "branch-instructions": 2566202800,
        "branch-misses": 5921797,
        "cycles": 8080595125,
        "instructions": 9287491408,
        "sysy_time": 5.398755,
        "task-clock": 5387.1
      },
      {
        "branch-instructions": 2566199508,
        "branch-misses": 5866428,
        "cycles": 8048540164,
        "instructions": 9287360368,
        "sysy_time": 5.377585,
        "task-clock": 5365.72
      },
      {
        "branch-instructions": 2566223008,
        "branch-misses": 5867261,
        "cycles": 8047900546,
        "instructions": 9287533617,
        "sysy_time": 5.376428,
        "task-clock": 5365.3
      }
    ],
    "0e074d4a00394405947f6ffe832756d20f133681": [
      {
        "sysy_time": 5.22397,
        "task-clock:u": 5196.91
      },
      {
        "sysy_time": 5.209893,
        "task-clock:u": 5180.39
      },
      {
        "sysy_time": 5.19972,
        "task-clock:u": 5168.81
      },
      {
        "sysy_time": 5.234861,
        "task-clock:u": 5199.5
      },
      {
        "sysy_time": 5.21244,
        "task-clock:u": 5177.9
      }
    ],
    "1c8acc1c21e3b23e27da33f663e1f7c2e06fbb42": [
      {
        "branch-instructions": 2565927634,
        "branch-misses": 5570401,
        "cycles": 7551687424,
        "instructions": 8778104191,
        "sysy_time": 5.046214,
        "task-clock": 5034.48
      },
      {
        "branch-instructions": 2566316732,
        "branch-misses": 5859429,
        "cycles": 7636035975,
        "instructions": 8781029073,
        "sysy_time": 5.091532,
        "task-clock": 5090.72
      },
      {
        "branch-instructions": 2565940634,
        "branch-misses": 5602067,
        "cycles": 7577094269,
        "instructions": 8778237908,
        "sysy_time": 5.063147,
        "task-clock": 5051.42
      },
      {
        "branch-instructions": 2565917601,
        "branch-misses": 5527225,
        "cycles": 7560005869,
        "instructions": 8778052340,
        "sysy_time": 5.051782,
        "task-clock": 5040.02
      },
      {
        "branch-instructions": 2565955724,
        "branch-misses": 5590064,
        "cycles": 7572483986,
        "instructions": 8778326471,
        "sysy_time": 5.059992,
        "task-clock": 5048.36
      }
    ],
    "2a366fcde60a2ddc6b0e99641976360fcf4e350a": [
      {
        "branch-instructions": 2565914075,
        "branch-misses": 5614718,
        "cycles": 7531848107,
        "instructions": 8777983778,
        "sysy_time": 5.033186,
        "task-clock": 5021.26
      },
      {
        "branch-instructions": 2566310102,
        "branch-misses": 5743425,
        "cycles": 7609975032,
        "instructions": 8780932119,
        "sysy_time": 5.074178,
        "task-clock": 5073.34
      },
      {
        "branch-instructions": 2566309556,
        "branch-misses": 5814631,
        "cycles": 7616966756,
        "instructions": 8781035954,
        "sysy_time": 5.078985,
        "task-clock": 5078.04
      },
      {
        "branch-instructions": 2565946477,
        "branch-misses": 5591416,
        "cycles": 7567157177,
        "instructions": 8778303854,
        "sysy_time": 5.05642,
        "task-clock": 5044.8
      },
      {
        "branch-instructions": 2565960562,
        "branch-misses": 5588281,
        "cycles": 7565251448,
        "instructions": 8778392055,
        "sysy_time": 5.054786,
        "task-clock": 5043.53
      }
    ],
    "2a4c1220efbc358e9291b1cff96acbddb07bfa83": [
      {
        "branch-instructions": 4104414043,
        "branch-misses": 9435488,
        "cycles": 13091686005,
        "instructions": 14960977962,
        "sysy_time": 8.739136,
        "task-clock": 8727.83
      },
      {
        "branch-instructions": 4104394315,
        "branch-misses": 9479183,
        "cycles": 13103204851,
        "instructions": 14960709979,
        "sysy_time": 8.747546,
        "task-clock": 8735.51
      },
      {
        "branch-instructions": 4104372746,
        "branch-misses": 9464817,
        "cycles": 13079436823,
        "instructions": 14960577068,
        "sysy_time": 8.731543,
        "task-clock": 8719.66
      },
      {
        "branch-instructions": 4104388274,
        "branch-misses": 9484478,
        "cycles": 13088806361,
        "instructions": 14960717546,
        "sysy_time": 8.738136,
        "task-clock": 8725.9
      },
      {
        "branch-instructions": 4104398678,
        "branch-misses": 9573586,
        "cycles": 13106271911,
        "instructions": 14960817571,
        "sysy_time": 8.749505,
        "task-clock": 8737.55
      }
    ],
    "2dec3aadf64ca2c11c5a9ec8c596b14ea4083756": [
      {
        "sysy_time": 5.27836,
        "task-clock:u": 5277.44
      },
      {
        "sysy_time": 5.263037,
        "task-clock:u": 5250.88
      },
      {
        "sysy_time": 5.260201,
        "task-clock:u": 5259.24
      },
      {
        "sysy_time": 5.283226,
        "task-clock:u": 5282.17
      },
      {
        "sysy_time": 5.260581,
        "task-clock:u": 5248.84
      }
    ],
    "330d08bc3362040b0b07f22319057a3ed8378fa2": [
      {
        "branch-instructions": 4623123519,
        "branch-misses": 11597696,
        "cycles": 16030644866,
        "instructions": 21685416390,
        "sysy_time": 10.700031,
        "task-clock": 10687.14
      },
      {
        "branch-instructions": 4623167600,
        "branch-misses": 11650908,
        "cycles": 16099489297,
        "instructions": 21685872448,
        "sysy_time": 10.745913,
        "task-clock": 10733.07
      },
      {
        "branch-instructions": 4623189352,
        "branch-misses": 11541582,
        "cycles": 16099567146,
        "instructions": 21685964119,
        "sysy_time": 10.745527,
        "task-clock": 10733.08
      },
      {
        "branch-instructions": 4623538972,
        "branch-misses": 11789118,
        "cycles": 16109287506,
        "instructions": 21688765652,
        "sysy_time": 10.740683,
        "task-clock": 10739.56
      },
      {
        "branch-instructions": 4623130306,
        "branch-misses": 11537354,
        "cycles": 16084672604,
        "instructions": 21685528151,
        "sysy_time": 10.735862,
        "task-clock": 10723.16
      }
    ],
    "359ba93c2bef3d49fe84792d782098eeeae6ec07": [
      {
        "branch-instructions": 2565795722,
        "branch-misses": 5576306,
        "cycles": 7657863042,
        "instructions": 8773287579,
        "sysy_time": 5.11646,
        "task-clock": 5105.26
      },
      {
        "branch-instructions": 2565779572,
        "branch-misses": 5558109,
        "cycles": 7671684295,
        "instructions": 8773315747,
        "sysy_time": 5.126326,
        "task-clock": 5114.48
      },
      {
        "branch-instructions": 2565823461,
        "branch-misses": 5607971,
        "cycles": 7667872420,
        "instructions": 8773597544,
        "sysy_time": 5.123236,
        "task-clock": 5111.94
      },
      {
        "branch-instructions": 2565786681,
        "branch-misses": 5549847,
        "cycles": 7643377216,
        "instructions": 8773300712,
        "sysy_time": 5.106929,
        "task-clock": 5095.61
      },
      {
        "branch-instructions": 2565811817,
        "branch-misses": 5580270,
        "cycles": 7670531700,
        "instructions": 8773555838,
        "sysy_time": 5.125713,
        "task-clock": 5113.72
      }
    ],
    "3871ff9cf9c1c34fb6ed0dfec1f715110c5c9fd6": [
      {
        "branch-instructions": 2565785527,
        "branch-misses": 5524596,
        "cycles": 7580010174,
        "instructions": 8771986775,
        "sysy_time": 5.065148,
        "task-clock": 5053.36
      },
      {
        "branch-instructions": 2565773183,
        "branch-misses": 5474495,
        "cycles": 7574094762,
        "instructions": 8771747177,
        "sysy_time": 5.060536,
        "task-clock": 5049.42
      },
      {
        "branch-instructions": 2566109327,
        "branch-misses": 5633968,
        "cycles": 7613362093,
        "instructions": 8774334317,
        "sysy_time": 5.076736,
        "task-clock": 5075.61
      },
      {
        "branch-instructions": 2565758864,
        "branch-misses": 5453027,
        "cycles": 7537842261,
        "instructions": 8771589728,
        "sysy_time": 5.036283,
        "task-clock": 5025.25
      },
      {
        "branch-instructions": 2565783226,
        "branch-misses": 5500690,
        "cycles": 7566415543,
        "instructions": 8771875270,
        "sysy_time": 5.055819,
        "task-clock": 5044.32
      }
    ],
    "3975bb1ca684ff43afb5ece896f5c4c9d6e6857a": [
      {
        "branch-instructions": 4623141520,
        "branch-misses": 11618401,
        "cycles": 16075262790,
        "instructions": 21685577279,
        "sysy_time": 10.72913,
        "task-clock": 10716.88
      },
      {
        "branch-instructions": 4623147760,
        "branch-misses": 11514947,
        "cycles": 16090447873,
        "instructions": 21685582359,
        "sysy_time": 10.739485,
        "task-clock": 10727.01
      },
      {
        "branch-instructions": 4623144282,
        "branch-misses": 11739350,
        "cycles": 16065842499,
        "instructions": 21685654477,
        "sysy_time": 10.723803,
        "task-clock": 10710.62
      },
      {
        "branch-instructions": 4623144987,
        "branch-misses": 11499777,
        "cycles": 16088413626,
        "instructions": 21685658169,
        "sysy_time": 10.738058,
        "task-clock": 10725.66
      },
      {
        "branch-instructions": 4623155362,
        "branch-misses": 11588216,
        "cycles": 16081088236,
        "instructions": 21685774559,
        "sysy_time": 10.732843,
        "task-clock": 10720.77
      }
    ],
    "48fc6979e4aa331d1f9c9ea955cc0134c53f3938": [
      {
        "branch-instructions": 4103889066,
        "branch-misses": 9156627,
        "cycles": 11860549324,
        "instructions": 14954844838,
        "sysy_time": 7.932329,
        "task-clock": 7907.44
      },
      {
        "branch-instructions": 4104753359,
        "branch-misses": 9939480,
        "cycles": 11885813254,
        "instructions": 14963178608,
        "sysy_time": 7.967769,
        "task-clock": 7923.97
      },
      {
        "branch-instructions": 4105019244,
        "branch-misses": 9998785,
        "cycles": 11897608300,
        "instructions": 14965051392,
        "sysy_time": 7.966537,
        "task-clock": 7931.98
      },
      {
        "branch-instructions": 4104809422,
        "branch-misses": 9824074,
        "cycles": 11891984844,
        "instructions": 14963543854,
        "sysy_time": 7.970841,
        "task-clock": 7928.53
      },
      {
        "branch-instructions": 4104971439,
        "branch-misses": 9787649,
        "cycles": 11891766263,
        "instructions": 14964726161,
        "sysy_time": 7.9671,
        "task-clock": 7928.32
      }
    ],
    "4b106fcbf076b8476a70bf0ff416aacbf0d9be77": [
      {
        "branch-instructions": 2565749509,
        "branch-misses": 5548081,
        "cycles": 7651015076,
        "instructions": 8773106195,
        "sysy_time": 5.112938,
        "task-clock": 5100.69
      },
      {
        "branch-instructions": 2565768315,
        "branch-misses": 5553795,
        "cycles": 7643244751,
        "instructions": 8773201559,
        "sysy_time": 5.107152,
        "task-clock": 5095.51
      },
      {
        "branch-instructions": 2565790150,
        "branch-misses": 5567565,
        "cycles": 7670500465,
        "instructions": 8773313289,
        "sysy_time": 5.125282,
        "task-clock": 5113.68
      },
      {
        "branch-instructions": 2566190911,
        "branch-misses": 5776470,
        "cycles": 7673763321,
        "instructions": 8776358634,
        "sysy_time": 5.116843,
        "task-clock": 5115.91
      },
      {
        "branch-instructions": 2566168218,
        "branch-misses": 5769529,
        "cycles": 7694109630,
        "instructions": 8776245298,
        "sysy_time": 5.130722,
        "task-clock": 5129.44
      }
    ],
    "56f1f4a5250836799b7e2815aee17e4595931d6c": [
      {
        "sysy_time": 5.042678,
        "task-clock:u": 5030.93
      },
      {
        "sysy_time": 5.049759,
        "task-clock:u": 5038.04
      },
      {
        "sysy_time": 5.027743,
        "task-clock:u": 5016.4
      },
      {
        "sysy_time": 5.042631,
        "task-clock:u": 5030.71
      },
      {
        "sysy_time": 5.048077,
        "task-clock:u": 5036.18
      }
    ],
    "585045d5bb19d320ea39ca6cdb4de014cb68a7a1": [
      {
        "branch-instructions": 3589167996,
        "branch-misses": 6208429,
        "cycles": 8605990525,
        "instructions": 8784852028,
        "sysy_time": 5.749456,
        "task-clock": 5737.36
      },
      {
        "branch-instructions": 3589503648,
        "branch-misses": 6382635,
        "cycles": 8686027178,
        "instructions": 8787444407,
        "sysy_time": 5.792212,
        "task-clock": 5790.71
      },
      {
        "branch-instructions": 3589574046,
        "branch-misses": 6383721,
        "cycles": 8687393101,
        "instructions": 8788003146,
        "sysy_time": 5.792972,
        "task-clock": 5791.63
      },
      {
        "branch-instructions": 3589546273,
        "branch-misses": 6451871,
        "cycles": 8693940693,
        "instructions": 8787890314,
        "sysy_time": 5.797216,
        "task-clock": 5796.04
      },
      {
        "branch-instructions": 3589551039,
        "branch-misses": 6484824,
        "cycles": 8692982220,
        "instructions": 8787909911,
        "sysy_time": 5.79661,
        "task-clock": 5795.4
      }
    ],
    "62ce6e90349d4d8d7b262a67b7f0f7f59d071607": [
      {
        "branch-instructions": 4105698174,
        "branch-misses": 10907537,
        "cycles": 13095524595,
        "instructions": 14973377015,
        "sysy_time": 8.771948,
        "task-clock": 8730.54
      },
      {
        "branch-instructions": 4106237613,
        "branch-misses": 10863372,
        "cycles": 13148865591,
        "instructions": 14977728427,
        "sysy_time": 8.790072,
        "task-clock": 8765.5
      },
      {
        "branch-instructions": 4105515813,
        "branch-misses": 10705643,
        "cycles": 13097230585,
        "instructions": 14971980877,
        "sysy_time": 8.776274,
        "task-clock": 8731.42
      },
      {
        "branch-instructions": 4106285011,
        "branch-misses": 10900177,
        "cycles": 13140615993,
        "instructions": 14978200032,
        "sysy_time": 8.792512,
        "task-clock": 8767.22
      },
      {
        "branch-instructions": 4105775915,
        "branch-misses": 10868523,
        "cycles": 13088729182,
        "instructions": 14973857512,
        "sysy_time": 8.764379,
        "task-clock": 8726.69
      }
    ],
    "68cba9aba7f9c31af280650e8b47dce79eaab030": [
      {
        "branch-instructions": 2566031043,
        "branch-misses": 5725772,
        "cycles": 7779139714,
        "instructions": 8779616235,
        "sysy_time": 5.197693,
        "task-clock": 5186.12
      },
      {
        "branch-instructions": 2566410695,
        "branch-misses": 5875159,
        "cycles": 7767584033,
        "instructions": 8782185270,
        "sysy_time": 5.179287,
        "task-clock": 5178.43
      },
      {
        "branch-instructions": 2566015413,
        "branch-misses": 5697849,
        "cycles": 7724495180,
        "instructions": 8779310942,
        "sysy_time": 5.160996,
        "task-clock": 5149.7
      },
      {
        "branch-instructions": 2566403270,
        "branch-misses": 5863282,
        "cycles": 7769581308,
        "instructions": 8782105667,
        "sysy_time": 5.180809,
        "task-clock": 5179.76
      },
      {
        "branch-instructions": 2565989666,
        "branch-misses": 5729506,
        "cycles": 7735499646,
        "instructions": 8779212618,
        "sysy_time": 5.169232,
        "task-clock": 5157.04
      }
    ],
    "69691ffe05325859c09ffdf2c52e25cb30c3594f": [
      {
        "branch-instructions": 2566191900,
        "branch-misses": 5935430,
        "cycles": 8035676207,
        "instructions": 9287346902,
        "sysy_time": 5.368984,
        "task-clock": 5357.14
      },
      {
        "branch-instructions": 2566229308,
        "branch-misses": 5889614,
        "cycles": 8064634867,
        "instructions": 9287553032,
        "sysy_time": 5.3876,
        "task-clock": 5376.44
      },
      {
        "branch-instructions": 2566219101,
        "branch-misses": 5930848,
        "cycles": 8068578187,
        "instructions": 9287509090,
        "sysy_time": 5.390988,
        "task-clock": 5379.1
      },
      {
        "branch-instructions": 2566197446,
        "branch-misses": 5982105,
        "cycles": 8083587277,
        "instructions": 9287318494,
        "sysy_time": 5.400193,
        "task-clock": 5389.09
      },
      {
        "branch-instructions": 2566203702,
        "branch-misses": 5959724,
        "cycles": 8104431764,
        "instructions": 9287454390,
        "sysy_time": 5.413988,
        "task-clock": 5402.98
      }
    ],
    "6d44124a80e777712e32d41c7e9e197da7e0edd5": [
      {
        "sysy_time": 5.0945,
        "task-clock:u": 5082.89
      },
      {
        "sysy_time": 5.100949,
        "task-clock:u": 5089.53
      },
      {
        "sysy_time": 5.082612,
        "task-clock:u": 5071.19
      },
      {
        "sysy_time": 5.096563,
        "task-clock:u": 5085.21
      },
      {
        "sysy_time": 5.101854,
        "task-clock:u": 5100.81
      }
    ],
    "7501d07d092337845cfebf755d1c0414e9cc3318": [
      {
        "branch-instructions": 2566219286,
        "branch-misses": 5937392,
        "cycles": 8059259928,
        "instructions": 9287488241,
        "sysy_time": 5.384366,
        "task-clock": 5372.86
      },
      {
        "branch-instructions": 2566225647,
        "branch-misses": 5950142,
        "cycles": 8056530111,
        "instructions": 9287564058,
        "sysy_time": 5.382177,
        "task-clock": 5371.05
      },
      {
        "branch-instructions": 2566220773,
        "branch-misses": 5898612,
        "cycles": 8048380976,
        "instructions": 9287485764,
        "sysy_time": 5.377088,
        "task-clock": 5365.61
      },
      {
        "branch-instructions": 2566541377,
        "branch-misses": 6130999,
        "cycles": 8097471636,
        "instructions": 9289858877,
        "sysy_time": 5.399257,
        "task-clock": 5398.35
      },
      {
        "branch-instructions": 2566164531,
        "branch-misses": 5909277,
        "cycles": 8057242181,
        "instructions": 9287129536,
        "sysy_time": 5.382979,
        "task-clock": 5371.52
      }
    ],
    "7772c5ac1efaeddccba4acf809de06b868b6c670": [
      {
        "branch-instructions": 2566235482,
        "branch-misses": 5948216,
        "cycles": 8106300100,
        "instructions": 9299623529,
        "sysy_time": 5.416157,
        "task-clock": 5404.23
      },
      {
        "branch-instructions": 2566251021,
        "branch-misses": 5942256,
        "cycles": 8110793097,
        "instructions": 9299731202,
        "sysy_time": 5.418681,
        "task-clock": 5407.22
      },
      {
        "branch-instructions": 2566266900,
        "branch-misses": 5968395,
        "cycles": 8120940897,
        "instructions": 9299861009,
        "sysy_time": 5.4248,
        "task-clock": 5413.99
      },
      {
        "branch-instructions": 2566247551,
        "branch-misses": 5981242,
        "cycles": 8121024319,
        "instructions": 9299739820,
        "sysy_time": 5.425287,
        "task-clock": 5414.04
      },
      {
        "branch-instructions": 2566601904,
        "branch-misses": 6157215,
        "cycles": 8171505426,
        "instructions": 9302520276,
        "sysy_time": 5.448556,
        "task-clock": 5447.7
      }
    ],
    "79d0c32350816fb89f5c807773c6ab5a17fc8c4b": [
      {
        "branch-instructions": 4625023105,
        "branch-misses": 12580371,
        "cycles": 16883566567,
        "instructions": 21701214381,
        "sysy_time": 11.274353,
        "task-clock": 11255.83
      },
      {
        "branch-instructions": 4624525426,
        "branch-misses": 12292939,
        "cycles": 16792567453,
        "instructions": 21697738082,
        "sysy_time": 11.208088,
        "task-clock": 11195.16
      },
      {
        "branch-instructions": 4627147648,
        "branch-misses": 14205351,
        "cycles": 16911657305,
        "instructions": 21720433693,
        "sysy_time": 11.317858,
        "task-clock": 11274.13
      },
      {
        "branch-instructions": 4624608218,
        "branch-misses": 12448625,
        "cycles": 16822472730,
        "instructions": 21698252622,
        "sysy_time": 11.225412,
        "task-clock": 11215.16
      },
      {
        "branch-instructions": 4625336159,
        "branch-misses": 12824157,
        "cycles": 16834542346,
        "instructions": 21703815795,
        "sysy_time": 11.236557,
        "task-clock": 11223.49
      }
    ],
    "7c8732a9ebf8b074b17f37b704c835f331beb655": [
      {
        "branch-instructions": 2566165836,
        "branch-misses": 5919620,
        "cycles": 8063396503,
        "instructions": 9287137837,
        "sysy_time": 5.387446,
        "task-clock": 5375.63
      },
      {
        "branch-instructions": 2566530958,
        "branch-misses": 6101341,
        "cycles": 8108118456,
        "instructions": 9289761800,
        "sysy_time": 5.406422,
        "task-clock": 5405.48
      },
      {
        "branch-instructions": 2566189665,
        "branch-misses": 5967706,
        "cycles": 8087302784,
        "instructions": 9287385427,
        "sysy_time": 5.402968,
        "task-clock": 5391.57
      },
      {
        "branch-instructions": 2566188793,
        "branch-misses": 5947475,
        "cycles": 8073556891,
        "instructions": 9287335301,
        "sysy_time": 5.393554,
        "task-clock": 5382.4
      },
      {
        "branch-instructions": 2566167772,
        "branch-misses": 5915550,
        "cycles": 8060652663,
        "instructions": 9287156910,
        "sysy_time": 5.385579,
        "task-clock": 5373.79
      }
    ],
    "89b6ae2d896b2eb9f6f435f6d3701a3ca6bc54fd": [
      {
        "branch-instructions": 3207109554,
        "branch-misses": 6063494,
        "cycles": 8386294189,
        "instructions": 8524299990,
        "sysy_time": 5.603244,
        "task-clock": 5590.89
      },
      {
        "branch-instructions": 3207096075,
        "branch-misses": 6082323,
        "cycles": 8341948907,
        "instructions": 8524128165,
        "sysy_time": 5.57327,
        "task-clock": 5561.33
      },
      {
        "branch-instructions": 3207415160,
        "branch-misses": 6203073,
        "cycles": 8404974289,
        "instructions": 8526999587,
        "sysy_time": 5.604558,
        "task-clock": 5603.28
      },
      {
        "branch-instructions": 3207116206,
        "branch-misses": 6061632,
        "cycles": 8382447568,
        "instructions": 8524332030,
        "sysy_time": 5.600784,
        "task-clock": 5588.33
      },
      {
        "branch-instructions": 3207430613,
        "branch-misses": 6265481,
        "cycles": 8415390557,
        "instructions": 8527180699,
        "sysy_time": 5.611719,
        "task-clock": 5610.26
      }
    ],
    "8bd479176093f2ff091a09a82fae0854053f90e9": [
      {
        "branch-instructions": 2565764389,
        "branch-misses": 5580445,
        "cycles": 7544022402,
        "instructions": 8777002187,
        "sysy_time": 5.041421,
        "task-clock": 5029.38
      },
      {
        "branch-instructions": 2565804776,
        "branch-misses": 5591767,
        "cycles": 7583150936,
        "instructions": 8777380566,
        "sysy_time": 5.067243,
        "task-clock": 5055.47
      },
      {
        "branch-instructions": 2565802151,
        "branch-misses": 5651102,
        "cycles": 7590771647,
        "instructions": 8777488269,
        "sysy_time": 5.072238,
        "task-clock": 5060.55
      },
      {
        "branch-instructions": 2565792266,
        "branch-misses": 5588626,
        "cycles": 7565766602,
        "instructions": 8777334371,
        "sysy_time": 5.055301,
        "task-clock": 5043.87
      },
      {
        "branch-instructions": 2565811888,
        "branch-misses": 5540958,
        "cycles": 7599350488,
        "instructions": 8777451914,
        "sysy_time": 5.077799,
        "task-clock": 5066.26
      }
    ],
    "8c4b091b59989c8090e2a0cab60f20ed9007ef26": [
      {
        "sysy_time": 5.27353,
        "task-clock:u": 5272.65
      },
      {
        "sysy_time": 5.248088,
        "task-clock:u": 5236.6
      },
      {
        "sysy_time": 5.257435,
        "task-clock:u": 5245.55
      },
      {
        "sysy_time": 5.274754,
        "task-clock:u": 5273.81
      },
      {
        "sysy_time": 5.257603,
        "task-clock:u": 5245.63
      }
    ],
    "94f8356dfee136d4257a21bba074d2aa79f29134": [
      {
        "branch-instructions": 2565801047,
        "branch-misses": 5585423,
        "cycles": 7631839577,
        "instructions": 8773341126,
        "sysy_time": 5.099121,
        "task-clock": 5087.93
      },
      {
        "branch-instructions": 2566171049,
        "branch-misses": 5802930,
        "cycles": 7683573012,
        "instructions": 8776344126,
        "sysy_time": 5.123348,
        "task-clock": 5122.42
      },
      {
        "branch-instructions": 2565741673,
        "branch-misses": 5524011,
        "cycles": 7625515657,
        "instructions": 8772831974,
        "sysy_time": 5.095323,
        "task-clock": 5083.7
      },
      {
        "branch-instructions": 2565816838,
        "branch-misses": 5584355,
        "cycles": 7654188593,
        "instructions": 8773554602,
        "sysy_time": 5.114648,
        "task-clock": 5102.83
      },
      {
        "branch-instructions": 2565781256,
        "branch-misses": 5574925,
        "cycles": 7658610824,
        "instructions": 8773240688,
        "sysy_time": 5.117432,
        "task-clock": 5105.78
      }
    ],
    "9ae3423d1a35cf507f68fe54715f47a05d4985a5": [
      {
        "sysy_time": 5.121243,
        "task-clock:u": 5120.28
      },
      {
        "sysy_time": 5.139818,
        "task-clock:u": 5138.9
      },
      {
        "sysy_time": 5.099953,
        "task-clock:u": 5087.86
      },
      {
        "sysy_time": 5.108088,
        "task-clock:u": 5096.19
      },
      {
        "sysy_time": 5.121585,
        "task-clock:u": 5110.24
      }
    ],
    "a91e65b0fca3872769dbf87485e5f29b11066c21": [
      {
        "branch-instructions": 4624869642,
        "branch-misses": 12642436,
        "cycles": 16880820065,
        "instructions": 21700553634,
        "sysy_time": 11.279023,
        "task-clock": 11253.95
      },
      {
        "branch-instructions": 4624817724,
        "branch-misses": 12456279,
        "cycles": 16885342013,
        "instructions": 21699222136,
        "sysy_time": 11.271388,
        "task-clock": 11256.96
      },
      {
        "branch-instructions": 4625708030,
        "branch-misses": 13415177,
        "cycles": 16848256626,
        "instructions": 21708905692,
        "sysy_time": 11.261971,
        "task-clock": 11232.63
      },
      {
        "branch-instructions": 4625215893,
        "branch-misses": 12963669,
        "cycles": 16879737594,
        "instructions": 21703913173,
        "sysy_time": 11.265625,
        "task-clock": 11253.57
      },
      {
        "branch-instructions": 4625123601,
        "branch-misses": 12790861,
        "cycles": 16864829895,
        "instructions": 21702800011,
        "sysy_time": 11.25468,
        "task-clock": 11243.29
      }
    ],
    "aa4929e70bd9e93a7b8952c78a68675eb0a06c7a": [
      {
        "branch-instructions": 2565901434,
        "branch-misses": 5564127,
        "cycles": 7560288119,
        "instructions": 8778004459,
        "sysy_time": 5.05235,
        "task-clock": 5040.24
      },
      {
        "branch-instructions": 2565971399,
        "branch-misses": 5601182,
        "cycles": 7586225892,
        "instructions": 8778512044,
        "sysy_time": 5.068585,
        "task-clock": 5057.52
      },
      {
        "branch-instructions": 2565906745,
        "branch-misses": 5551671,
        "cycles": 7581613156,
        "instructions": 8778040542,
        "sysy_time": 5.066445,
        "task-clock": 5054.43
      },
      {
        "branch-instructions": 2565928394,
        "branch-misses": 5571427,
        "cycles": 7581057364,
        "instructions": 8778098548,
        "sysy_time": 5.0649,
        "task-clock": 5054.06
      },
      {
        "branch-instructions": 2566288219,
        "branch-misses": 5735433,
        "cycles": 7631993753,
        "instructions": 8780877839,
        "sysy_time": 5.088953,
        "task-clock": 5088.06
      }
    ],
    "af8b91b4620da08b94c69b91b94816f8381329b3": [
      {
        "sysy_time": 5.04145,
        "task-clock:u": 5030.02
      },
      {
        "sysy_time": 5.056346,
        "task-clock:u": 5044.34
      },
      {
        "sysy_time": 5.064333,
        "task-clock:u": 5063.27
      },
      {
        "sysy_time": 5.050727,
        "task-clock:u": 5038.68
      },
      {
        "sysy_time": 5.060438,
        "task-clock:u": 5059.41
      }
    ],
    "bce500a6d9c5c2d0e588d8368e4d74f5161a274c": [
      {
        "branch-instructions": 2566309675,
        "branch-misses": 5749933,
        "cycles": 7611428493,
        "instructions": 8780600938,
        "sysy_time": 5.075424,
        "task-clock": 5074.32
      },
      {
        "branch-instructions": 2566282666,
        "branch-misses": 5788839,
        "cycles": 7610027080,
        "instructions": 8780428543,
        "sysy_time": 5.074368,
        "task-clock": 5073.42
      },
      {
        "branch-instructions": 2565886144,
        "branch-misses": 5557576,
        "cycles": 7540559238,
        "instructions": 8777477382,
        "sysy_time": 5.038554,
        "task-clock": 5027.06
      },
      {
        "branch-instructions": 2565907923,
        "branch-misses": 5557191,
        "cycles": 7572094544,
        "instructions": 8777643499,
        "sysy_time": 5.059431,
        "task-clock": 5048.09
      },
      {
        "branch-instructions": 2565919564,
        "branch-misses": 5585610,
        "cycles": 7576764448,
        "instructions": 8777775922,
        "sysy_time": 5.062862,
        "task-clock": 5051.2
      }
    ],
    "c58d6e3fcf2833166cd5a77a4339ea219c222756": [
      {
        "branch-instructions": 4624607211,
        "branch-misses": 12188239,
        "cycles": 16158451940,
        "instructions": 21696961942,
        "sysy_time": 10.787246,
        "task-clock": 10772.4
      },
      {
        "branch-instructions": 4625458721,
        "branch-misses": 12944383,
        "cycles": 16152991273,
        "instructions": 21704938133,
        "sysy_time": 10.792221,
        "task-clock": 10769.0
      },
      {
        "branch-instructions": 4625107010,
        "branch-misses": 12743975,
        "cycles": 16147175071,
        "instructions": 21701836317,
        "sysy_time": 10.783009,
        "task-clock": 10764.96
      },
      {
        "branch-instructions": 4624045953,
        "branch-misses": 11881643,
        "cycles": 16135126911,
        "instructions": 21692836027,
        "sysy_time": 10.766735,
        "task-clock": 10756.9
      },
      {
        "branch-instructions": 4624078385,
        "branch-misses": 11960161,
        "cycles": 16135250735,
        "instructions": 21693202355,
        "sysy_time": 10.768792,
        "task-clock": 10757.02
      }
    ],
    "c96cca659b32392bef240df81d7dab107a91d02e": [
      {
        "branch-instructions": 2565908311,
        "branch-misses": 5602327,
        "cycles": 7572268214,
        "instructions": 8777962268,
        "sysy_time": 5.059584,
        "task-clock": 5048.21
      },
      {
        "branch-instructions": 2565928029,
        "branch-misses": 5590701,
        "cycles": 7575330837,
        "instructions": 8778088790,
        "sysy_time": 5.061596,
        "task-clock": 5050.25
      },
      {
        "branch-instructions": 2565952716,
        "branch-misses": 5594947,
        "cycles": 7599774052,
        "instructions": 8778297511,
        "sysy_time": 5.077768,
        "task-clock": 5066.55
      },
      {
        "branch-instructions": 2565924314,
        "branch-misses": 5646324,
        "cycles": 7580482079,
        "instructions": 8778087112,
        "sysy_time": 5.065019,
        "task-clock": 5053.68
      },
      {
        "branch-instructions": 2565895547,
        "branch-misses": 5534391,
        "cycles": 7536032996,
        "instructions": 8777803703,
        "sysy_time": 5.03586,
        "task-clock": 5024.05
      }
    ],
    "cd9001b7b00e54e9b5a06a8a4054a2903805d8ee": [
      {
        "branch-instructions": 3589175437,
        "branch-misses": 6142085,
        "cycles": 8597490427,
        "instructions": 9802827886,
        "sysy_time": 5.743579,
        "task-clock": 5731.69
      },
      {
        "branch-instructions": 3589169482,
        "branch-misses": 6182266,
        "cycles": 8596139649,
        "instructions": 9802840099,
        "sysy_time": 5.742745,
        "task-clock": 5730.8
      },
      {
        "branch-instructions": 3589151535,
        "branch-misses": 6195854,
        "cycles": 8572692512,
        "instructions": 9802656263,
        "sysy_time": 5.727403,
        "task-clock": 5715.15
      },
      {
        "branch-instructions": 3589169944,
        "branch-misses": 6191730,
        "cycles": 8598715788,
        "instructions": 9802811074,
        "sysy_time": 5.744513,
        "task-clock": 5732.52
      },
      {
        "branch-instructions": 3589145913,
        "branch-misses": 6153342,
        "cycles": 8600532491,
        "instructions": 9802638599,
        "sysy_time": 5.746041,
        "task-clock": 5733.71
      }
    ],
    "d3a7f546540e264c70b455207ad10d54f4d4f580": [
      {
        "branch-instructions": 4105514256,
        "branch-misses": 10346059,
        "cycles": 12667799460,
        "instructions": 15994759597,
        "sysy_time": 8.482121,
        "task-clock": 8445.88
      },
      {
        "branch-instructions": 4105079295,
        "branch-misses": 10071012,
        "cycles": 12673784665,
        "instructions": 15990818673,
        "sysy_time": 8.475614,
        "task-clock": 8449.76
      },
      {
        "branch-instructions": 4105532976,
        "branch-misses": 10486187,
        "cycles": 12656305738,
        "instructions": 15995051079,
        "sysy_time": 8.474255,
        "task-clock": 8438.53
      },
      {
        "branch-instructions": 4105935642,
        "branch-misses": 10661811,
        "cycles": 12704499485,
        "instructions": 15998457414,
        "sysy_time": 8.495089,
        "task-clock": 8470.64
      },
      {
        "branch-instructions": 4105957940,
        "branch-misses": 10533225,
        "cycles": 12715178165,
        "instructions": 15998723446,
        "sysy_time": 8.502147,
        "task-clock": 8477.42
      }
    ],
    "d40d138db693f396a43e7c1ff30dda6468ceb38b": [
      {
        "branch-instructions": 4103749344,
        "branch-misses": 8565887,
        "cycles": 11838015836,
        "instructions": 12399790792,
        "sysy_time": 7.904008,
        "task-clock": 7892.05
      },
      {
        "branch-instructions": 4103746340,
        "branch-misses": 8577460,
        "cycles": 11811348329,
        "instructions": 12399641216,
        "sysy_time": 7.886122,
        "task-clock": 7874.27
      },
      {
        "branch-instructions": 4104133842,
        "branch-misses": 8758858,
        "cycles": 11875737090,
        "instructions": 12403008183,
        "sysy_time": 7.918254,
        "task-clock": 7917.19
      },
      {
        "branch-instructions": 4103756214,
        "branch-misses": 8709489,
        "cycles": 11863652988,
        "instructions": 12399884856,
        "sysy_time": 7.920867,
        "task-clock": 7909.14
      },
      {
        "branch-instructions": 4103744662,
        "branch-misses": 8657055,
        "cycles": 11852398364,
        "instructions": 12399767601,
        "sysy_time": 7.914121,
        "task-clock": 7901.64
      }
    ],
    "d59c49feebe67bdca8b7a92cca1d865c892253fb": [
      {
        "branch-instructions": 4623500049,
        "branch-misses": 11806266,
        "cycles": 16127794231,
        "instructions": 21688659536,
        "sysy_time": 10.752937,
        "task-clock": 10751.92
      },
      {
        "branch-instructions": 4623145049,
        "branch-misses": 11636947,
        "cycles": 16083571034,
        "instructions": 21685618840,
        "sysy_time": 10.735434,
        "task-clock": 10722.43
      },
      {
        "branch-instructions": 4623143623,
        "branch-misses": 11597304,
        "cycles": 16096531591,
        "instructions": 21685680591,
        "sysy_time": 10.743849,
        "task-clock": 10731.07
      },
      {
        "branch-instructions": 4623174001,
        "branch-misses": 11666901,
        "cycles": 16085492849,
        "instructions": 21685906945,
        "sysy_time": 10.736405,
        "task-clock": 10723.71
      },
      {
        "branch-instructions": 4623177235,
        "branch-misses": 11689511,
        "cycles": 16073806140,
        "instructions": 21685920362,
        "sysy_time": 10.728517,
        "task-clock": 10715.93
      }
    ],
    "df1be2c1cfc7dbadc189533186f436ba5ed148c8": [
      {
        "sysy_time": 5.06122,
        "task-clock:u": 5060.27
      },
      {
        "sysy_time": 5.03791,
        "task-clock:u": 5026.32
      },
      {
        "sysy_time": 5.032054,
        "task-clock:u": 5020.33
      },
      {
        "sysy_time": 5.037579,
        "task-clock:u": 5025.53
      },
      {
        "sysy_time": 5.029366,
        "task-clock:u": 5018.07
      }
    ],
    "e46e2b118091eda5eca2c29ea8eae8a2fee0892b": [
      {
        "branch-instructions": 2564163454,
        "branch-misses": 5546863,
        "cycles": 7621076509,
        "instructions": 8257780807,
        "sysy_time": 5.092315,
        "task-clock": 5080.75
      },
      {
        "branch-instructions": 2564161470,
        "branch-misses": 5530072,
        "cycles": 7620513919,
        "instructions": 8257659616,
        "sysy_time": 5.092048,
        "task-clock": 5080.37
      },
      {
        "branch-instructions": 2564143471,
        "branch-misses": 5557013,
        "cycles": 7600567522,
        "instructions": 8257502812,
        "sysy_time": 5.078969,
        "task-clock": 5067.07
      },
      {
        "branch-instructions": 2564141983,
        "branch-misses": 5479025,
        "cycles": 7590150478,
        "instructions": 8257475291,
        "sysy_time": 5.07263,
        "task-clock": 5060.13
      },
      {
        "branch-instructions": 2564239088,
        "branch-misses": 5504753,
        "cycles": 7593655374,
        "instructions": 8258087778,
        "sysy_time": 5.074135,
        "task-clock": 5062.47
      }
    ],
    "e7cd8719f78bec7d1916df3c060ff95f0c04246b": [
      {
        "branch-instructions": 3589539759,
        "branch-misses": 6383752,
        "cycles": 8608656138,
        "instructions": 9805624063,
        "sysy_time": 5.740293,
        "task-clock": 5739.15
      },
      {
        "branch-instructions": 3589156139,
        "branch-misses": 6217755,
        "cycles": 8596321788,
        "instructions": 9802801418,
        "sysy_time": 5.742675,
        "task-clock": 5730.91
      },
      {
        "branch-instructions": 3589138105,
        "branch-misses": 6239463,
        "cycles": 8566069451,
        "instructions": 9802592833,
        "sysy_time": 5.722666,
        "task-clock": 5710.74
      },
      {
        "branch-instructions": 3589161952,
        "branch-misses": 6255274,
        "cycles": 8597549261,
        "instructions": 9802789779,
        "sysy_time": 5.743559,
        "task-clock": 5731.73
      },
      {
        "branch-instructions": 3589153244,
        "branch-misses": 6226377,
        "cycles": 8580882038,
        "instructions": 9802744145,
        "sysy_time": 5.732308,
        "task-clock": 5720.63
      }
    ],
    "e8ebd9dd60dc7659813f32a85aac1ff3cc8bd428": [
      {
        "branch-instructions": 3589872156,
        "branch-misses": 6823471,
        "cycles": 9225402486,
        "instructions": 9813130150,
        "sysy_time": 6.151882,
        "task-clock": 6150.37
      },
      {
        "branch-instructions": 3589470973,
        "branch-misses": 6590221,
        "cycles": 9160071709,
        "instructions": 9810311120,
        "sysy_time": 6.118836,
        "task-clock": 6106.77
      },
      {
        "branch-instructions": 3589472363,
        "branch-misses": 6658605,
        "cycles": 9211432061,
        "instructions": 9810615283,
        "sysy_time": 6.153703,
        "task-clock": 6140.98
      },
      {
        "branch-instructions": 3589485441,
        "branch-misses": 6617484,
        "cycles": 9182977047,
        "instructions": 9810515044,
        "sysy_time": 6.134355,
        "task-clock": 6122.02
      },
      {
        "branch-instructions": 3589508139,
        "branch-misses": 6694398,
        "cycles": 9198171313,
        "instructions": 9810691835,
        "sysy_time": 6.143725,
        "task-clock": 6132.14
      }
    ]
  },
  "gcc": [
    {
      "branch-misses": 4305147,
      "branches": 2562778218,
      "cycles": 5716817195,
      "instructions": 7732783160,
      "sysy_time": 3.82814,
      "task-clock": 3811.23
    },
    {
      "branch-misses": 4356494,
      "branches": 2562792211,
      "cycles": 5774445371,
      "instructions": 7733196211,
      "sysy_time": 3.866251,
      "task-clock": 3849.65
    },
    {
      "branch-misses": 4341854,
      "branches": 2562888478,
      "cycles": 5799557530,
      "instructions": 7734305645,
      "sysy_time": 3.873474,
      "task-clock": 3866.39
    },
    {
      "branch-misses": 4371015,
      "branches": 2562896018,
      "cycles": 5811199260,
      "instructions": 7734416550,
      "sysy_time": 3.881273,
      "task-clock": 3874.16
    },
    {
      "branch-misses": 4293192,
      "branches": 2562846729,
      "cycles": 5756324885,
      "instructions": 7733453009,
      "sysy_time": 3.855256,
      "task-clock": 3837.57
    }
  ]
}