{
  "data": {
    "2a4c1220efbc358e9291b1cff96acbddb07bfa83": [
      {
        "branch-instructions": 10004209556,
        "branch-misses": 18508922,
        "cycles": 26015789705,
        "instructions": 25141754155,
        "sysy_time": 17.365892,
        "task-clock": 17343.9
      },
      {
        "branch-instructions": 10006017803,
        "branch-misses": 18400836,
        "cycles": 26038131523,
        "instructions": 25146422882,
        "sysy_time": 17.378226,
        "task-clock": 17358.8
      },
      {
        "branch-instructions": 10005899259,
        "branch-misses": 18846331,
        "cycles": 26016580986,
        "instructions": 25145586960,
        "sysy_time": 17.362358,
        "task-clock": 17344.43
      },
      {
        "branch-instructions": 10006456155,
        "branch-misses": 18560236,
        "cycles": 26041512119,
        "instructions": 25147531818,
        "sysy_time": 17.378769,
        "task-clock": 17361.05
      },
      {
        "branch-instructions": 10006065940,
        "branch-misses": 18502464,
        "cycles": 26014897731,
        "instructions": 25146446744,
        "sysy_time": 17.362134,
        "task-clock": 17343.31
      }
    ],
    "330d08bc3362040b0b07f22319057a3ed8378fa2": [
      {
        "branch-instructions": 10008349688,
        "branch-misses": 18439858,
        "cycles": 25990750862,
        "instructions": 25151506580,
        "sysy_time": 17.338786,
        "task-clock": 17327.22
      },
      {
        "branch-instructions": 10006095193,
        "branch-misses": 18762687,
        "cycles": 26035157426,
        "instructions": 25146696905,
        "sysy_time": 17.375639,
        "task-clock": 17356.81
      },
      {
        "branch-instructions": 10005922654,
        "branch-misses": 18664428,
        "cycles": 25983192491,
        "instructions": 25146081461,
        "sysy_time": 17.340959,
        "task-clock": 17322.17
      },
      {
        "branch-instructions": 10004252328,
        "branch-misses": 18488869,
        "cycles": 25983570050,
        "instructions": 25142053344,
        "sysy_time": 17.344854,
        "task-clock": 17322.42
      },
      {
        "branch-instructions": 10008830214,
        "branch-misses": 18518575,
        "cycles": 25994737462,
        "instructions": 25153339310,
        "sysy_time": 17.341076,
        "task-clock": 17329.88
      }
    ],
    "3975bb1ca684ff43afb5ece896f5c4c9d6e6857a": [
      {
        "branch-instructions": 10006474214,
        "branch-misses": 18669448,
        "cycles": 26205662664,
        "instructions": 25148183698,
        "sysy_time": 17.48764,
        "task-clock": 17470.48
      },
      {
        "branch-instructions": 10006383941,
        "branch-misses": 18504497,
        "cycles": 25988786560,
        "instructions": 25147321417,
        "sysy_time": 17.344077,
        "task-clock": 17325.89
      },
      {
        "branch-instructions": 10006139319,
        "branch-misses": 18424311,
        "cycles": 25988044898,
        "instructions": 25146557710,
        "sysy_time": 17.344212,
        "task-clock": 17325.42
      },
      {
        "branch-instructions": 10008549788,
        "branch-misses": 18547441,
        "cycles": 26045639065,
        "instructions": 25152751004,
        "sysy_time": 17.375086,
        "task-clock": 17363.79
      },
      {
        "branch-instructions": 10006250620,
        "branch-misses": 18609008,
        "cycles": 25977674266,
        "instructions": 25146759388,
        "sysy_time": 17.33717,
        "task-clock": 17318.49
      }
    ],
    "48fc6979e4aa331d1f9c9ea955cc0134c53f3938": [
      {
        "branch-instructions": 10004344325,
        "branch-misses": 21569206,
        "cycles": 26056667715,
        "instructions": 25161657351,
        "sysy_time": 17.425789,
        "task-clock": 17369.83
      },
      {
        "branch-instructions": 10007908943,
        "branch-misses": 20978011,
        "cycles": 26014878006,
        "instructions": 25169802963,
        "sysy_time": 17.390841,
        "task-clock": 17341.99
      },
      {
        "branch-instructions": 10008493521,
        "branch-misses": 21037911,
        "cycles": 26062651187,
        "instructions": 25171874785,
        "sysy_time": 17.422703,
        "task-clock": 17373.82
      },
      {
        "branch-instructions": 10007768185,
        "branch-misses": 20994995,
        "cycles": 26066619794,
        "instructions": 25170241873,
        "sysy_time": 17.427109,
        "task-clock": 17376.43
      },
      {
        "branch-instructions": 10004291542,
        "branch-misses": 21067684,
        "cycles": 26016208090,
        "instructions": 25160736556,
        "sysy_time": 17.39854,
        "task-clock": 17342.86
      }
    ],
    "62ce6e90349d4d8d7b262a67b7f0f7f59d071607": [
      {
        "branch-instructions": 10011402311,
        "branch-misses": 20932108,
        "cycles": 26034414498,
        "instructions": 25178895566,
        "sysy_time": 17.395834,
        "task-clock": 17355.06
      },
      {
        "branch-instructions": 10009142309,
        "branch-misses": 20957488,
        "cycles": 26026559911,
        "instructions": 25172845825,
        "sysy_time": 17.396506,
        "task-clock": 17349.77
      },
      {
        "branch-instructions": 10009154426,
        "branch-misses": 21096777,
        "cycles": 26029769216,
        "instructions": 25173551096,
        "sysy_time": 17.399586,
        "task-clock": 17351.81
      },
      {
        "branch-instructions": 10007779946,
        "branch-misses": 20564000,
        "cycles": 26020698064,
        "instructions": 25167357656,
        "sysy_time": 17.391004,
        "task-clock": 17346.06
      },
      {
        "branch-instructions": 10006914372,
        "branch-misses": 20750345,
        "cycles": 26019482972,
        "instructions": 25167032496,
        "sysy_time": 17.395149,
        "task-clock": 17345.03
      }
    ],
    "79d0c32350816fb89f5c807773c6ab5a17fc8c4b": [
      {
        "branch-instructions": 10010848760,
        "branch-misses": 18868398,
        "cycles": 26008567941,
        "instructions": 25164217444,
        "sysy_time": 17.357861,
        "task-clock": 17339.0
      },
      {
        "branch-instructions": 10007476210,
        "branch-misses": 18818906,
        "cycles": 25994252587,
        "instructions": 25154290241,
        "sysy_time": 17.357586,
        "task-clock": 17329.45
      },
      {
        "branch-instructions": 10013714395,
        "branch-misses": 22090229,
        "cycles": 26075241558,
        "instructions": 25196756543,
        "sysy_time": 17.437424,
        "task-clock": 17382.05
      },
      {
        "branch-instructions": 10013234920,
        "branch-misses": 21662610,
        "cycles": 26064927331,
        "instructions": 25193533050,
        "sysy_time": 17.426086,
        "task-clock": 17375.43
      },
      {
        "branch-instructions": 10009917803,
        "branch-misses": 19178295,
        "cycles": 26012169338,
        "instructions": 25163933583,
        "sysy_time": 17.389701,
        "task-clock": 17341.3
      }
    ],
    "7c8732a9ebf8b074b17f37b704c835f331beb655": [
      {
        "branch-instructions": 10007508028,
        "branch-misses": 19455845,
        "cycles": 27420652116,
        "instructions": 25157037255,
        "sysy_time": 18.298766,
        "task-clock": 18280.49
      },
      {
        "branch-instructions": 10007334892,
        "branch-misses": 19688506,
        "cycles": 27421593110,
        "instructions": 25156814672,
        "sysy_time": 18.300173,
        "task-clock": 18281.11
      },
      {
        "branch-instructions": 10009848378,
        "branch-misses": 19448614,
        "cycles": 27429200098,
        "instructions": 25162892461,
        "sysy_time": 18.297123,
        "task-clock": 18286.17
      },
      {
        "branch-instructions": 10007315900,
        "branch-misses": 19539497,
        "cycles": 27424055871,
        "instructions": 25156907469,
        "sysy_time": 18.30156,
        "task-clock": 18282.75
      },
      {
        "branch-instructions": 10006650353,
        "branch-misses": 19454228,
        "cycles": 27417986990,
        "instructions": 25155100253,
        "sysy_time": 18.298702,
        "task-clock": 18278.7
      }
    ],
    "a91e65b0fca3872769dbf87485e5f29b11066c21": [
      {
        "branch-instructions": 10014738035,
        "branch-misses": 22558927,
        "cycles": 26088916664,
        "instructions": 25203791814,
        "sysy_time": 17.450139,
        "task-clock": 17391.16
      },
      {
        "branch-instructions": 10010135960,
        "branch-misses": 19168371,
        "cycles": 26015066187,
        "instructions": 25164924320,
        "sysy_time": 17.369926,
        "task-clock": 17343.27
      },
      {
        "branch-instructions": 10009496715,
        "branch-misses": 19211714,
        "cycles": 26010229992,
        "instructions": 25163004979,
        "sysy_time": 17.412001,
        "task-clock": 17339.87
      },
      {
        "branch-instructions": 10015529666,
        "branch-misses": 22111847,
        "cycles": 26080137304,
        "instructions": 25200737671,
        "sysy_time": 17.443549,
        "task-clock": 17385.35
      },
      {
        "branch-instructions": 10009451796,
        "branch-misses": 18925758,
        "cycles": 26008211075,
        "instructions": 25160217000,
        "sysy_time": 17.356265,
        "task-clock": 17338.82
      }
    ],
    "c58d6e3fcf2833166cd5a77a4339ea219c222756": [
      {
        "branch-instructions": 10012249831,
        "branch-misses": 20707786,
        "cycles": 27440459012,
        "instructions": 25182407417,
        "sysy_time": 18.320113,
        "task-clock": 18293.27
      },
      {
        "branch-instructions": 10010770373,
        "branch-misses": 19848030,
        "cycles": 27445933531,
        "instructions": 25170434969,
        "sysy_time": 18.319524,
        "task-clock": 18297.29
      },
      {
        "branch-instructions": 10014233729,
        "branch-misses": 19975845,
        "cycles": 27458027933,
        "instructions": 25179652519,
        "sysy_time": 18.315652,
        "task-clock": 18305.33
      },
      {
        "branch-instructions": 10013581644,
        "branch-misses": 20687644,
        "cycles": 27456915404,
        "instructions": 25182047535,
        "sysy_time": 18.32476,
        "task-clock": 18304.34
      },
      {
        "branch-instructions": 10010767200,
        "branch-misses": 19783705,
        "cycles": 27446327629,
        "instructions": 25170246541,
        "sysy_time": 18.311939,
        "task-clock": 18297.58
      }
    ],
    "d3a7f546540e264c70b455207ad10d54f4d4f580": [
      {
        "branch-instructions": 10008642145,
        "branch-misses": 21142702,
        "cycles": 26026662214,
        "instructions": 25171633744,
        "sysy_time": 17.397314,
        "task-clock": 17349.83
      },
      {
        "branch-instructions": 10006540540,
        "branch-misses": 21404305,
        "cycles": 26063776333,
        "instructions": 25167190082,
        "sysy_time": 17.426894,
        "task-clock": 17374.54
      },
      {
        "branch-instructions": 10008725637,
        "branch-misses": 21175502,
        "cycles": 26071138595,
        "instructions": 25172637914,
        "sysy_time": 17.427656,
        "task-clock": 17379.46
      },
      {
        "branch-instructions": 10004205103,
        "branch-misses": 21240763,
        "cycles": 26058843560,
        "instructions": 25161122332,
        "sysy_time": 17.427201,
        "task-clock": 17371.23
      },
      {
        "branch-instructions": 10011287416,
        "branch-misses": 20840040,
        "cycles": 26079601596,
        "instructions": 25178853995,
        "sysy_time": 17.426307,
        "task-clock": 17385.15
      }
    ],
    "d40d138db693f396a43e7c1ff30dda6468ceb38b": [
      {
        "branch-instructions": 10006155719,
        "branch-misses": 18326501,
        "cycles": 25976482788,
        "instructions": 25146687252,
        "sysy_time": 17.336572,
        "task-clock": 17317.69
      },
      {
        "branch-instructions": 10004087030,
        "branch-misses": 18450283,
        "cycles": 25970483259,
        "instructions": 25141436481,
        "sysy_time": 17.335727,
        "task-clock": 17313.71
      },
      {
        "branch-instructions": 10005915006,
        "branch-misses": 18481166,
        "cycles": 25975366151,
        "instructions": 25146072678,
        "sysy_time": 17.33592,
        "task-clock": 17316.96
      },
      {
        "branch-instructions": 10006041699,
        "branch-misses": 18547129,
        "cycles": 25976280223,
        "instructions": 25146415005,
        "sysy_time": 17.336861,
        "task-clock": 17317.56
      },
      {
        "branch-instructions": 10006210160,
        "branch-misses": 18385407,
        "cycles": 25977378109,
        "instructions": 25146889542,
        "sysy_time": 17.336585,
        "task-clock": 17318.28
      }
    ],
    "d59c49feebe67bdca8b7a92cca1d865c892253fb": [
      {
        "branch-instructions": 10007352957,
        "branch-misses": 19610057,
        "cycles": 27418948274,
        "instructions": 25156817823,
        "sysy_time": 18.297873,
        "task-clock": 18279.36
      },
      {
        "branch-instructions": 10007512010,
        "branch-misses": 19541052,
        "cycles": 27419412183,
        "instructions": 25156973426,
        "sysy_time": 18.297688,
        "task-clock": 18279.65
      },
      {
        "branch-instructions": 10007083973,
        "branch-misses": 19443900,
        "cycles": 27418430505,
        "instructions": 25156037343,
        "sysy_time": 18.298149,
        "task-clock": 18279.0
      },
      {
        "branch-instructions": 10007281643,
        "branch-misses": 19612805,
        "cycles": 27424116518,
        "instructions": 25156807413,
        "sysy_time": 18.301595,
        "task-clock": 18282.79
      },
      {
        "branch-instructions": 10007525130,
        "branch-misses": 19468981,
        "cycles": 27408066138,
        "instructions": 25157349630,
        "sysy_time": 18.290271,
        "task-clock": 18272.1
      }
    ]
  },
  "gcc": [
    {
      "branch-misses": 19046135,
      "branches": 7821222100,
      "cycles": 26657788698,
      "instructions": 33271110751,
      "sysy_time": 17.790588,
      "task-clock": 17771.9
    },
    {
      "branch-misses": 20198085,
      "branches": 7816861668,
      "cycles": 28311062940,
      "instructions": 33259111178,
      "sysy_time": 18.905154,
      "task-clock": 18874.08
    },
    {
      "branch-misses": 18889834,
      "branches": 7821045011,
      "cycles": 26665739503,
      "instructions": 33271010110,
      "sysy_time": 17.795996,
      "task-clock": 17777.2
    },
    {
      "branch-misses": 20082320,
      "branches": 7822571957,
      "cycles": 28341734380,
      "instructions": 33284381110,
      "sysy_time": 18.913431,
      "task-clock": 18894.55
    },
    {
      "branch-misses": 20321924,
      "branches": 7822530132,
      "cycles": 28339828463,
      "instructions": 33284317707,
      "sysy_time": 18.911893,
      "task-clock": 18893.29
    }
  ]
}