{
  "data": {
    "2a4c1220efbc358e9291b1cff96acbddb07bfa83": [
      {
        "branch-instructions": 541428312,
        "branch-misses": 9735364,
        "cycles": 8576440322,
        "instructions": 9180686782,
        "sysy_time": 5.718435,
        "task-clock": 5717.67
      },
      {
        "branch-instructions": 540561287,
        "branch-misses": 9628527,
        "cycles": 8562829906,
        "instructions": 9165859295,
        "sysy_time": 5.720178,
        "task-clock": 5708.56
      },
      {
        "branch-instructions": 540590333,
        "branch-misses": 9653013,
        "cycles": 8564008297,
        "instructions": 9166432014,
        "sysy_time": 5.72022,
        "task-clock": 5709.35
      },
      {
        "branch-instructions": 541429586,
        "branch-misses": 9728973,
        "cycles": 8577382480,
        "instructions": 9180638577,
        "sysy_time": 5.719099,
        "task-clock": 5718.3
      },
      {
        "branch-instructions": 540557531,
        "branch-misses": 9677021,
        "cycles": 8563589335,
        "instructions": 9165933297,
        "sysy_time": 5.720499,
        "task-clock": 5709.07
      }
    ],
    "330d08bc3362040b0b07f22319057a3ed8378fa2": [
      {
        "branch-instructions": 540625255,
        "branch-misses": 9704496,
        "cycles": 8564475280,
        "instructions": 9166969692,
        "sysy_time": 5.720586,
        "task-clock": 5709.66
      },
      {
        "branch-instructions": 540588490,
        "branch-misses": 9520625,
        "cycles": 8561625913,
        "instructions": 9166368159,
        "sysy_time": 5.718786,
        "task-clock": 5707.76
      },
      {
        "branch-instructions": 540619685,
        "branch-misses": 9711068,
        "cycles": 8564842240,
        "instructions": 9166974200,
        "sysy_time": 5.720591,
        "task-clock": 5709.91
      },
      {
        "branch-instructions": 541474822,
        "branch-misses": 9701403,
        "cycles": 8576803509,
        "instructions": 9180983463,
        "sysy_time": 5.718762,
        "task-clock": 5717.92
      },
      {
        "branch-instructions": 540581004,
        "branch-misses": 9687957,
        "cycles": 8563199927,
        "instructions": 9166145746,
        "sysy_time": 5.720243,
        "task-clock": 5708.81
      }
    ],
    "3975bb1ca684ff43afb5ece896f5c4c9d6e6857a": [
      {
        "branch-instructions": 540552540,
        "branch-misses": 9691215,
        "cycles": 8563605565,
        "instructions": 9165834600,
        "sysy_time": 5.72051,
        "task-clock": 5709.08
      },
      {
        "branch-instructions": 541452855,
        "branch-misses": 9754237,
        "cycles": 8577527479,
        "instructions": 9180786935,
        "sysy_time": 5.719168,
        "task-clock": 5718.4
      },
      {
        "branch-instructions": 540629118,
        "branch-misses": 9680381,
        "cycles": 8563334435,
        "instructions": 9167002753,
        "sysy_time": 5.719792,
        "task-clock": 5708.9
      },
      {
        "branch-instructions": 540604160,
        "branch-misses": 9715892,
        "cycles": 8563237304,
        "instructions": 9166593735,
        "sysy_time": 5.719952,
        "task-clock": 5708.84
      },
      {
        "branch-instructions": 541479359,
        "branch-misses": 9762075,
        "cycles": 8578454301,
        "instructions": 9181006551,
        "sysy_time": 5.71984,
        "task-clock": 5719.02
      }
    ],
    "48fc6979e4aa331d1f9c9ea955cc0134c53f3938": [
      {
        "branch-instructions": 541062910,
        "branch-misses": 13478020,
        "cycles": 8610555955,
        "instructions": 9167291286,
        "sysy_time": 5.765428,
        "task-clock": 5739.8
      },
      {
        "branch-instructions": 541003138,
        "branch-misses": 10514085,
        "cycles": 8569611140,
        "instructions": 9166343977,
        "sysy_time": 5.738549,
        "task-clock": 5712.54
      },
      {
        "branch-instructions": 541062086,
        "branch-misses": 10388253,
        "cycles": 8569791037,
        "instructions": 9167240573,
        "sysy_time": 5.73858,
        "task-clock": 5712.65
      },
      {
        "branch-instructions": 542425509,
        "branch-misses": 10387215,
        "cycles": 8591090346,
        "instructions": 9189890868,
        "sysy_time": 5.744143,
        "task-clock": 5732.83
      },
      {
        "branch-instructions": 541001942,
        "branch-misses": 10346008,
        "cycles": 8568472838,
        "instructions": 9166328768,
        "sysy_time": 5.738028,
        "task-clock": 5711.79
      }
    ],
    "62ce6e90349d4d8d7b262a67b7f0f7f59d071607": [
      {
        "branch-instructions": 541046429,
        "branch-misses": 10386389,
        "cycles": 8569379650,
        "instructions": 9167092873,
        "sysy_time": 5.737859,
        "task-clock": 5712.37
      },
      {
        "branch-instructions": 541490825,
        "branch-misses": 10543858,
        "cycles": 8577212884,
        "instructions": 9174635253,
        "sysy_time": 5.738264,
        "task-clock": 5717.59
      },
      {
        "branch-instructions": 542385968,
        "branch-misses": 10469054,
        "cycles": 8591507014,
        "instructions": 9189653721,
        "sysy_time": 5.737604,
        "task-clock": 5727.18
      },
      {
        "branch-instructions": 542397334,
        "branch-misses": 10450639,
        "cycles": 8590977870,
        "instructions": 9189655332,
        "sysy_time": 5.73733,
        "task-clock": 5726.85
      },
      {
        "branch-instructions": 542402725,
        "branch-misses": 10345091,
        "cycles": 8590305196,
        "instructions": 9189686843,
        "sysy_time": 5.736847,
        "task-clock": 5726.4
      }
    ],
    "79d0c32350816fb89f5c807773c6ab5a17fc8c4b": [
      {
        "branch-instructions": 543176247,
        "branch-misses": 10669486,
        "cycles": 8603977327,
        "instructions": 9195441572,
        "sysy_time": 5.749917,
        "task-clock": 5735.45
      },
      {
        "branch-instructions": 542285983,
        "branch-misses": 10009901,
        "cycles": 8588219554,
        "instructions": 9187258111,
        "sysy_time": 5.732558,
        "task-clock": 5725.3
      },
      {
        "branch-instructions": 543880943,
        "branch-misses": 11404800,
        "cycles": 8613731366,
        "instructions": 9198317875,
        "sysy_time": 5.772282,
        "task-clock": 5741.54
      },
      {
        "branch-instructions": 541980430,
        "branch-misses": 9765324,
        "cycles": 8585227801,
        "instructions": 9184454011,
        "sysy_time": 5.727286,
        "task-clock": 5723.45
      },
      {
        "branch-instructions": 541760686,
        "branch-misses": 9668345,
        "cycles": 8581809479,
        "instructions": 9182896791,
        "sysy_time": 5.725915,
        "task-clock": 5721.21
      }
    ],
    "a91e65b0fca3872769dbf87485e5f29b11066c21": [
      {
        "branch-instructions": 541703687,
        "branch-misses": 9670153,
        "cycles": 8583063739,
        "instructions": 9182607468,
        "sysy_time": 5.727493,
        "task-clock": 5722.04
      },
      {
        "branch-instructions": 541905755,
        "branch-misses": 9673570,
        "cycles": 8583611082,
        "instructions": 9183893948,
        "sysy_time": 5.724234,
        "task-clock": 5722.41
      },
      {
        "branch-instructions": 541769740,
        "branch-misses": 9742027,
        "cycles": 8583360928,
        "instructions": 9183531277,
        "sysy_time": 5.733025,
        "task-clock": 5722.19
      },
      {
        "branch-instructions": 541751178,
        "branch-misses": 9690672,
        "cycles": 8582179318,
        "instructions": 9182769553,
        "sysy_time": 5.723383,
        "task-clock": 5721.48
      },
      {
        "branch-instructions": 540943191,
        "branch-misses": 9664840,
        "cycles": 8568963403,
        "instructions": 9168704503,
        "sysy_time": 5.723735,
        "task-clock": 5712.64
      }
    ],
    "c58d6e3fcf2833166cd5a77a4339ea219c222756": [
      {
        "branch-instructions": 541898658,
        "branch-misses": 9690586,
        "cycles": 8583004716,
        "instructions": 9183868697,
        "sysy_time": 5.724569,
        "task-clock": 5722.01
      },
      {
        "branch-instructions": 541957579,
        "branch-misses": 9818448,
        "cycles": 8584809167,
        "instructions": 9184774174,
        "sysy_time": 5.727081,
        "task-clock": 5723.1
      },
      {
        "branch-instructions": 542893290,
        "branch-misses": 10510727,
        "cycles": 8599770079,
        "instructions": 9193765692,
        "sysy_time": 5.750351,
        "task-clock": 5732.66
      },
      {
        "branch-instructions": 543043700,
        "branch-misses": 10774106,
        "cycles": 8603574497,
        "instructions": 9194503776,
        "sysy_time": 5.749522,
        "task-clock": 5735.21
      },
      {
        "branch-instructions": 541711789,
        "branch-misses": 9693972,
        "cycles": 8582390091,
        "instructions": 9182950275,
        "sysy_time": 5.726844,
        "task-clock": 5721.6
      }
    ],
    "d3a7f546540e264c70b455207ad10d54f4d4f580": [
      {
        "branch-instructions": 541513023,
        "branch-misses": 10509449,
        "cycles": 8578166917,
        "instructions": 9174845695,
        "sysy_time": 5.739307,
        "task-clock": 5718.19
      },
      {
        "branch-instructions": 541541953,
        "branch-misses": 10440598,
        "cycles": 8578781678,
        "instructions": 9175547409,
        "sysy_time": 5.738896,
        "task-clock": 5718.66
      },
      {
        "branch-instructions": 540677831,
        "branch-misses": 10418838,
        "cycles": 8563955404,
        "instructions": 9160959797,
        "sysy_time": 5.738088,
        "task-clock": 5708.73
      },
      {
        "branch-instructions": 542364533,
        "branch-misses": 10356119,
        "cycles": 8589895512,
        "instructions": 9189434416,
        "sysy_time": 5.742733,
        "task-clock": 5732.38
      },
      {
        "branch-instructions": 540659091,
        "branch-misses": 10443702,
        "cycles": 8563654059,
        "instructions": 9160611776,
        "sysy_time": 5.738078,
        "task-clock": 5708.57
      }
    ],
    "d40d138db693f396a43e7c1ff30dda6468ceb38b": [
      {
        "branch-instructions": 540620815,
        "branch-misses": 9574099,
        "cycles": 8562873324,
        "instructions": 9166903278,
        "sysy_time": 5.719501,
        "task-clock": 5708.59
      },
      {
        "branch-instructions": 540639004,
        "branch-misses": 9533786,
        "cycles": 8563492326,
        "instructions": 9167157762,
        "sysy_time": 5.719813,
        "task-clock": 5709.01
      },
      {
        "branch-instructions": 540597145,
        "branch-misses": 9709992,
        "cycles": 8564219452,
        "instructions": 9166423781,
        "sysy_time": 5.720567,
        "task-clock": 5709.49
      },
      {
        "branch-instructions": 540582839,
        "branch-misses": 9707769,
        "cycles": 8563037703,
        "instructions": 9166219569,
        "sysy_time": 5.720053,
        "task-clock": 5708.7
      },
      {
        "branch-instructions": 540565596,
        "branch-misses": 9668779,
        "cycles": 8562693932,
        "instructions": 9166032210,
        "sysy_time": 5.719976,
        "task-clock": 5708.47
      }
    ],
    "d59c49feebe67bdca8b7a92cca1d865c892253fb": [
      {
        "branch-instructions": 541432833,
        "branch-misses": 9482399,
        "cycles": 8576613007,
        "instructions": 9180674837,
        "sysy_time": 5.718557,
        "task-clock": 5717.79
      },
      {
        "branch-instructions": 540561963,
        "branch-misses": 9522265,
        "cycles": 8563267101,
        "instructions": 9165914868,
        "sysy_time": 5.720526,
        "task-clock": 5708.85
      },
      {
        "branch-instructions": 540591679,
        "branch-misses": 9512988,
        "cycles": 8564601472,
        "instructions": 9166537259,
        "sysy_time": 5.720914,
        "task-clock": 5709.75
      },
      {
        "branch-instructions": 540588837,
        "branch-misses": 9523620,
        "cycles": 8564025290,
        "instructions": 9166445105,
        "sysy_time": 5.720508,
        "task-clock": 5709.37
      },
      {
        "branch-instructions": 540633971,
        "branch-misses": 9473775,
        "cycles": 8565015359,
        "instructions": 9167160302,
        "sysy_time": 5.720768,
        "task-clock": 5710.02
      }
    ]
  },
  "gcc": [
    {
      "branch-misses": 2131422,
      "branches": 250751995,
      "cycles": 2996045241,
      "instructions": 2046261461,
      "sysy_time": 2.014291,
      "task-clock": 1997.37
    },
    {
      "branch-misses": 2197716,
      "branches": 251456273,
      "cycles": 3004679293,
      "instructions": 2052086669,
      "sysy_time": 2.013667,
      "task-clock": 2003.16
    },
    {
      "branch-misses": 2196034,
      "branches": 250378944,
      "cycles": 2992103405,
      "instructions": 2043139243,
      "sysy_time": 2.014765,
      "task-clock": 1994.74
    },
    {
      "branch-misses": 2109917,
      "branches": 250828619,
      "cycles": 2996899959,
      "instructions": 2046884620,
      "sysy_time": 2.014305,
      "task-clock": 1997.94
    },
    {
      "branch-misses": 2181647,
      "branches": 250928993,
      "cycles": 2998490717,
      "instructions": 2047712703,
      "sysy_time": 2.014756,
      "task-clock": 1999.0
    }
  ]
}