{
  "data": {
    "3975bb1ca684ff43afb5ece896f5c4c9d6e6857a": [
      {
        "branch-instructions": 77946652,
        "branch-misses": 957799,
        "cycles": 1257643531,
        "instructions": 1186404034,
        "sysy_time": 0.84921,
        "task-clock": 838.43
      },
      {
        "branch-instructions": 77981626,
        "branch-misses": 938069,
        "cycles": 1254439733,
        "instructions": 1186785174,
        "sysy_time": 0.846944,
        "task-clock": 836.29
      },
      {
        "branch-instructions": 78019718,
        "branch-misses": 930239,
        "cycles": 1255314692,
        "instructions": 1187489800,
        "sysy_time": 0.846996,
        "task-clock": 836.88
      },
      {
        "branch-instructions": 78837123,
        "branch-misses": 986393,
        "cycles": 1269295006,
        "instructions": 1199743392,
        "sysy_time": 0.846864,
        "task-clock": 846.23
      },
      {
        "branch-instructions": 78034825,
        "branch-misses": 941392,
        "cycles": 1255567548,
        "instructions": 1187626503,
        "sysy_time": 0.847051,
        "task-clock": 837.04
      }
    ],
    "79d0c32350816fb89f5c807773c6ab5a17fc8c4b": [
      {
        "branch-instructions": 79128522,
        "branch-misses": 1981680,
        "cycles": 1330514576,
        "instructions": 1190350317,
        "sysy_time": 0.891532,
        "task-clock": 886.95
      },
      {
        "branch-instructions": 79144699,
        "branch-misses": 1422384,
        "cycles": 1322797898,
        "instructions": 1190487945,
        "sysy_time": 0.88568,
        "task-clock": 881.78
      },
      {
        "branch-instructions": 79148949,
        "branch-misses": 1491422,
        "cycles": 1324636022,
        "instructions": 1190468347,
        "sysy_time": 0.886113,
        "task-clock": 883.03
      },
      {
        "branch-instructions": 79121819,
        "branch-misses": 1226103,
        "cycles": 1320564150,
        "instructions": 1190092629,
        "sysy_time": 0.88342,
        "task-clock": 880.31
      },
      {
        "branch-instructions": 79166670,
        "branch-misses": 2060091,
        "cycles": 1331427525,
        "instructions": 1190668606,
        "sysy_time": 0.89167,
        "task-clock": 887.54
      }
    ],
    "a91e65b0fca3872769dbf87485e5f29b11066c21": [
      {
        "branch-instructions": 78956928,
        "branch-misses": 1410626,
        "cycles": 1328171866,
        "instructions": 1176640549,
        "sysy_time": 0.886595,
        "task-clock": 885.49
      },
      {
        "branch-instructions": 79122958,
        "branch-misses": 1270697,
        "cycles": 1326292235,
        "instructions": 1178235172,
        "sysy_time": 0.893502,
        "task-clock": 884.11
      },
      {
        "branch-instructions": 78514012,
        "branch-misses": 1192202,
        "cycles": 1317927287,
        "instructions": 1170355819,
        "sysy_time": 0.884769,
        "task-clock": 878.63
      },
      {
        "branch-instructions": 78975864,
        "branch-misses": 1392980,
        "cycles": 1326509527,
        "instructions": 1176907204,
        "sysy_time": 0.886207,
        "task-clock": 884.34
      },
      {
        "branch-instructions": 78899957,
        "branch-misses": 1282555,
        "cycles": 1325956968,
        "instructions": 1176130410,
        "sysy_time": 0.885558,
        "task-clock": 884.0
      }
    ],
    "c58d6e3fcf2833166cd5a77a4339ea219c222756": [
      {
        "branch-instructions": 78890102,
        "branch-misses": 959981,
        "cycles": 1270682610,
        "instructions": 1200119617,
        "sysy_time": 0.848103,
        "task-clock": 847.15
      },
      {
        "branch-instructions": 78864391,
        "branch-misses": 997563,
        "cycles": 1269350593,
        "instructions": 1199859891,
        "sysy_time": 0.84761,
        "task-clock": 846.27
      },
      {
        "branch-instructions": 78899535,
        "branch-misses": 998334,
        "cycles": 1269765900,
        "instructions": 1200359603,
        "sysy_time": 0.853359,
        "task-clock": 846.48
      },
      {
        "branch-instructions": 78872925,
        "branch-misses": 963445,
        "cycles": 1269017674,
        "instructions": 1200009252,
        "sysy_time": 0.846997,
        "task-clock": 846.04
      },
      {
        "branch-instructions": 78878690,
        "branch-misses": 950607,
        "cycles": 1271768362,
        "instructions": 1200057334,
        "sysy_time": 0.848785,
        "task-clock": 847.88
      }
    ],
    "d59c49feebe67bdca8b7a92cca1d865c892253fb": [
      {
        "branch-instructions": 78024479,
        "branch-misses": 925969,
        "cycles": 1255311250,
        "instructions": 1187453917,
        "sysy_time": 0.847053,
        "task-clock": 836.87
      },
      {
        "branch-instructions": 77961773,
        "branch-misses": 884243,
        "cycles": 1253724041,
        "instructions": 1186607071,
        "sysy_time": 0.846498,
        "task-clock": 835.82
      },
      {
        "branch-instructions": 78852678,
        "branch-misses": 1011200,
        "cycles": 1269058107,
        "instructions": 1199912727,
        "sysy_time": 0.846718,
        "task-clock": 846.07
      },
      {
        "branch-instructions": 77965750,
        "branch-misses": 939751,
        "cycles": 1254406841,
        "instructions": 1186644487,
        "sysy_time": 0.846891,
        "task-clock": 836.27
      },
      {
        "branch-instructions": 78839479,
        "branch-misses": 979731,
        "cycles": 1268953862,
        "instructions": 1199796319,
        "sysy_time": 0.846684,
        "task-clock": 846.01
      }
    ]
  },
  "gcc": [
    {
      "branch-misses": 614610,
      "branches": 60869426,
      "cycles": 783565309,
      "instructions": 619711043,
      "sysy_time": 0.541232,
      "task-clock": 522.38
    },
    {
      "branch-misses": 643687,
      "branches": 61203403,
      "cycles": 788476800,
      "instructions": 623084390,
      "sysy_time": 0.541578,
      "task-clock": 525.65
    },
    {
      "branch-misses": 634578,
      "branches": 61182970,
      "cycles": 788369193,
      "instructions": 622876292,
      "sysy_time": 0.54155,
      "task-clock": 525.58
    },
    {
      "branch-misses": 637091,
      "branches": 61170780,
      "cycles": 788201321,
      "instructions": 622752740,
      "sysy_time": 0.541568,
      "task-clock": 525.47
    },
    {
      "branch-misses": 638067,
      "branches": 61195462,
      "cycles": 788072975,
      "instructions": 622972924,
      "sysy_time": 0.541436,
      "task-clock": 525.38
    }
  ]
}