{
  "arm": {
    "113483ade1c34ea82f3db51a354e1176dad083e4": {
      "branch-load-misses:u": 632,
      "branch-loads:u": 389900836,
      "cycles:u": 5813658058,
      "iTLB-load-misses:u": 79,
      "inst_retired:u": 13226586264,
      "inst_spec:u": 13226650986,
      "instructions:u": 13226595154,
      "sysy_time": 3.896579,
      "task-clock:u": 3890.86
    },
    "346de76b54aa92b9bd5fa523ad686c48ee9b6af6": {
      "branch-load-misses": 73989,
      "branch-loads": 393183348,
      "cycles": 5807096469,
      "iTLB-load-misses": 3947,
      "inst_retired": 13212864711,
      "inst_spec": 13215701876,
      "instructions": 13212876742,
      "sysy_time": 3.880868,
      "task-clock": 3875.56
    },
    "377826e4b87e1b09d4f811708c15375e9d09a15f": {
      "branch-load-misses:u": 693,
      "branch-loads:u": 389969463,
      "cycles:u": 5820004418,
      "iTLB-load-misses:u": 76,
      "inst_retired:u": 13228910665,
      "inst_spec:u": 13228979991,
      "instructions:u": 13228919417,
      "sysy_time": 3.90087,
      "task-clock:u": 3895.22
    },
    "48d1d909299606555ee6fd868cbcd8648fe7ee9d": {
      "branch-load-misses:u": 674,
      "branch-loads:u": 389900594,
      "cycles:u": 5820075547,
      "iTLB-load-misses:u": 84,
      "inst_retired:u": 13226574528,
      "inst_spec:u": 13226641228,
      "instructions:u": 13226583007,
      "sysy_time": 3.901474,
      "task-clock:u": 3895.55
    },
    "dd9b2f32d438b1ffef8fbfaa80e9fbf25e2cd104": {
      "branch-load-misses:u": 667,
      "branch-loads:u": 389890971,
      "cycles:u": 5818547354,
      "iTLB-load-misses:u": 78,
      "inst_retired:u": 13226252171,
      "inst_spec:u": 13226317671,
      "instructions:u": 13226261393,
      "sysy_time": 3.899655,
      "task-clock:u": 3893.67
    },
    "f5456db3e19187aa4d028032103b60006886a52b": {
      "branch-load-misses:u": 697,
      "branch-loads:u": 389898898,
      "cycles:u": 5818658057,
      "iTLB-load-misses:u": 76,
      "inst_retired:u": 13226521466,
      "inst_spec:u": 13226590321,
      "instructions:u": 13226531617,
      "sysy_time": 3.89979,
      "task-clock:u": 3893.87
    }
  },
  "arm_gcc": {
    "branch-load-misses": 48658,
    "branch-loads": 122030900,
    "cycles": 3497297237,
    "iTLB-load-misses": 4079,
    "inst_retired": 3098305183,
    "inst_spec": 3103055083,
    "instructions": 3098311282,
    "sysy_time": 2.338159,
    "task-clock": 2334.55
  }
}